{
  "extensionId": "d0bb90fc-a605-465f-a90d-d51c16d7b7b9",
  "extensionName": "Theme-TomorrowKit",
  "publisherName": "ms-vscode",
  "displayName": "Tomorrow and Tomorrow Night Theme Kit",
  "version": "0.1.4",
  "extractedAt": "2026-02-08T00:10:43.279Z",
  "installCount": 208900,
  "themes": [
    {
      "name": "Tomorrow",
      "label": "Tomorrow",
      "colors": {
        "editor.background": "#FFFFFF",
        "editor.foreground": "#4D4D4C"
      },
      "type": "light"
    },
    {
      "name": "Tomorrow Night Eighties",
      "label": "Tomorrow Night Eighties",
      "colors": {
        "editor.background": "#2D2D2D",
        "editor.foreground": "#CCCCCC"
      },
      "type": "dark"
    },
    {
      "name": "Tomorrow Night",
      "label": "Tomorrow Night",
      "colors": {
        "editor.background": "#1D1F21",
        "editor.foreground": "#C5C8C6"
      },
      "type": "dark"
    },
    {
      "name": "Tomorrow Night Bright",
      "label": "Tomorrow Night Bright",
      "colors": {
        "editor.background": "#000000",
        "editor.foreground": "#DEDEDE"
      },
      "type": "dark"
    }
  ],
  "source": "marketplace"
}
