{
  "extensionId": "2fe23fc1-a83e-4ed4-82d6-d1529fdc9d9b",
  "extensionName": "spotify-color-theme",
  "publisherName": "oguhpereira",
  "displayName": "Spotify Theme",
  "version": "1.3.0",
  "extractedAt": "2026-02-08T00:11:12.599Z",
  "installCount": 4044,
  "themes": [
    {
      "name": "Spotify Theme",
      "label": "Spotify Theme",
      "colors": {
        "editor.background": "#212121",
        "editor.foreground": "#B3B3B3",
        "titleBar.activeBackground": "#535353",
        "titleBar.activeForeground": "#B3B3B3",
        "titleBar.inactiveBackground": "#535353",
        "titleBar.inactiveForeground": "#B3B3B3",
        "statusBar.background": "#212121",
        "statusBar.foreground": "#B3B3B3",
        "statusBar.border": "#1DB954",
        "activityBar.background": "#121212",
        "activityBar.foreground": "#B3B3B3",
        "activityBar.activeBorder": "#1DB954",
        "sideBar.background": "#121212",
        "sideBar.foreground": "#B3B3B3",
        "sideBar.border": "#212121",
        "sideBarSectionHeader.background": "#121212",
        "sideBarSectionHeader.foreground": "#B3B3B3",
        "sideBarSectionHeader.border": "#212121"
      },
      "type": "dark"
    },
    {
      "name": "Spotify Theme Soft",
      "label": "Spotify Theme Soft",
      "colors": {
        "editor.background": "#212121",
        "editor.foreground": "#B3B3B3",
        "titleBar.activeBackground": "#535353",
        "titleBar.activeForeground": "#B3B3B3",
        "titleBar.inactiveBackground": "#535353",
        "titleBar.inactiveForeground": "#B3B3B3",
        "statusBar.background": "#212121",
        "statusBar.foreground": "#B3B3B3",
        "statusBar.border": "#1DB954",
        "activityBar.background": "#121212",
        "activityBar.foreground": "#B3B3B3",
        "activityBar.activeBorder": "#1DB954",
        "sideBar.background": "#121212",
        "sideBar.foreground": "#B3B3B3",
        "sideBar.border": "#212121",
        "sideBarSectionHeader.background": "#121212",
        "sideBarSectionHeader.foreground": "#B3B3B3",
        "sideBarSectionHeader.border": "#212121"
      },
      "type": "dark"
    }
  ],
  "source": "openvsx"
}
